pytypes_env/__init__.py
pytypes_env-0.0.5.dist-info/METADATA
pytypes_env-0.0.5.dist-info/WHEEL
pytypes_env-0.0.5.dist-info/top_level.txt
pytypes_env-0.0.5.dist-info/RECORD
